jamsuite/__init__.py
jamsuite/logger/__init__.py
jamsuite/logger/colors.py
jamsuite/logger/formatters.py
jamsuite/logger/helpers.py
jamsuite/logger/mixins.py
jamsuite/logger/serializers.py
jamsuite_logger-0.9.0.dist-info/METADATA
jamsuite_logger-0.9.0.dist-info/WHEEL
jamsuite_logger-0.9.0.dist-info/licenses/LICENSE
jamsuite_logger-0.9.0.dist-info/RECORD
