Metadata-Version: 2.4
Name: jamsuite-logger
Version: 0.9.0
Summary: JSON structured logger
Project-URL: Homepage, https://github.com/JamSuite/jamsuite-logger
Project-URL: Documentation, https://github.com/JamSuite/jamsuite-logger#readme
Project-URL: Repository, https://github.com/JamSuite/jamsuite-logger
Project-URL: Issues, https://github.com/JamSuite/jamsuite-logger/issues
Author-email: JamSuite Developers <opensource@jamsuite.com>
Maintainer-email: JamSuite Developers <opensource@jamsuite.com>
License: Apache-2.0 License
License-File: LICENSE
Keywords: jamsuite,json-logger,logger,logging,structured-logger
Classifier: Development Status :: 4 - Beta
Classifier: Intended Audience :: Developers
Classifier: License :: OSI Approved :: Apache Software License
Classifier: Programming Language :: Python :: 3
Classifier: Programming Language :: Python :: 3.8
Classifier: Programming Language :: Python :: 3.9
Classifier: Programming Language :: Python :: 3.10
Classifier: Programming Language :: Python :: 3.11
Classifier: Programming Language :: Python :: 3.12
Classifier: Programming Language :: Python :: 3.13
Classifier: Programming Language :: Python :: 3.14
Classifier: Topic :: System :: Logging
Requires-Python: >=3.8
